quantagonia/__init__.py
quantagonia/enums.py
quantagonia/parameters.py
quantagonia/runner.py
quantagonia/runner_factory.py
quantagonia/cloud/__init__.py
quantagonia/cloud/cloud_runner.py
quantagonia/cloud/enums.py
quantagonia/cloud/https_client.py
quantagonia/cloud/solver_log.py
quantagonia/cloud/specs_enums.py
quantagonia/cloud/specs_https_client.py
quantagonia/cloud/dto/__init__.py
quantagonia/cloud/dto/encoder.py
quantagonia/cloud/dto/job.py
quantagonia/cloud/dto/presigned_s3.py
quantagonia/errors/__init__.py
quantagonia/errors/errors.py
quantagonia/examples/async_qubo.py
quantagonia/examples/import_dwave_bqm.py
quantagonia/examples/import_pyqubo.py
quantagonia/examples/import_qiskit_qubo.py
quantagonia/examples/model_mip.py
quantagonia/examples/model_qubo.py
quantagonia/examples/solve_ip_as_qubo.py
quantagonia/examples/solve_mps.py
quantagonia/examples/solve_qubo.py
quantagonia/examples/solve_qubo_monitored.py
quantagonia/examples/submit_and_check_mps.py
quantagonia/examples/submit_batched.py
quantagonia/examples/submit_mps.py
quantagonia/examples/submit_qubo.py
quantagonia/examples/submit_qubo_monitored.py
quantagonia/examples/data/example.mps
quantagonia/examples/data/example.qubo
quantagonia/examples/data/example_monitor.qubo
quantagonia/examples/data/garbage.mps
quantagonia/examples/data/ip_as_qubo.lp
quantagonia/local/__init__.py
quantagonia/local/enums.py
quantagonia/local/local_runner.py
quantagonia/mip/__init__.py
quantagonia/mip/pulp_adapter.py
quantagonia/parser/__init__.py
quantagonia/parser/log_parser.py
quantagonia/parser/solution_parser.py
quantagonia/pulp/__init__.py
quantagonia/pulp/hybrid_solver_api.py
quantagonia/pulp/qpulp_adapter.py
quantagonia/qubo/__init__.py
quantagonia/qubo/expression.py
quantagonia/qubo/model.py
quantagonia/qubo/overloads.py
quantagonia/qubo/term.py
quantagonia/qubo/variable.py
quantagonia_api_client-0.85.data/scripts/hybridsolver
quantagonia_api_client-0.85.dist-info/LICENSE
quantagonia_api_client-0.85.dist-info/METADATA
quantagonia_api_client-0.85.dist-info/WHEEL
quantagonia_api_client-0.85.dist-info/top_level.txt
quantagonia_api_client-0.85.dist-info/RECORD
