Metadata-Version: 2.1
Name: quantagonia-api-client
Version: 0.85
Summary: This package contains APIs for accessing Quantagonia's HybridSolver for solving MIPs and QUBOs through native file formats or PuLP resp. PyQUBO, Qiskit, or Ocean
Home-page: https://www.quantagonia.com
Author: Quantagonia GmbH
Author-email: apis@quantagonia.com
Keywords: Optimization,Linear Programming,Operations Research
Classifier: Development Status :: 5 - Production/Stable
Classifier: Environment :: Console
Classifier: Intended Audience :: Science/Research
Classifier: License :: OSI Approved :: BSD License
Classifier: Natural Language :: English
Classifier: Programming Language :: Python
Classifier: Topic :: Scientific/Engineering :: Mathematics
License-File: LICENSE
Requires-Dist: requests
Requires-Dist: urllib3 >=1.26
Requires-Dist: pyqubo
Requires-Dist: pulp
Requires-Dist: yaspin
Requires-Dist: qiskit
Requires-Dist: qiskit-optimization
Requires-Dist: dwave-ocean-sdk
Requires-Dist: concurrencytest
Requires-Dist: parameterized
Requires-Dist: typer[all]
Requires-Dist: singledispatchmethod ; python_version <= "3.7"
